landing_zone/__init__.py
landing_zone/conf.py
landing_zone/gdb_api.py
landing_zone/main.py
landing_zone-1.0.0.dist-info/LICENSE
landing_zone-1.0.0.dist-info/METADATA
landing_zone-1.0.0.dist-info/WHEEL
landing_zone-1.0.0.dist-info/entry_points.txt
landing_zone-1.0.0.dist-info/RECORD
