Metadata-Version: 2.1
Name: landing-zone
Version: 1.0.0
Summary: Checks if a user input reaches a specified function; requires gdb
Author: bluesentinelsec
Author-email: bluesentinel@protonmail.com
Requires-Python: >=3.9,<4.0
Classifier: Programming Language :: Python :: 3
Classifier: Programming Language :: Python :: 3.9
Classifier: Programming Language :: Python :: 3.10
Classifier: Programming Language :: Python :: 3.11
Requires-Dist: pygdbmi (>=0.11.0.0,<0.12.0.0)
Requires-Dist: pyyaml (>=6.0,<7.0)
